babble/__init__.py
babble/auth.py
babble/client.py
babble/config.py
babble/crypto/__init__.py
babble/crypto/exceptions.py
babble/crypto/hashfuncs.py
babble/crypto/identity.py
babble/encoding.py
babble/mailbox.py
fetchai_babble-0.4.5.dist-info/LICENSE
fetchai_babble-0.4.5.dist-info/METADATA
fetchai_babble-0.4.5.dist-info/WHEEL
fetchai_babble-0.4.5.dist-info/RECORD
