Metadata-Version: 2.3
Name: fetchai-babble
Version: 0.4.5
Summary: A simple python library for interacting with the Fetch.ai messaging service (called Memorandum)
License: Apache 2.0
Author: Fetch.AI Limited
Requires-Python: >=3.10,<4.0
Classifier: License :: Other/Proprietary License
Classifier: Programming Language :: Python :: 3
Classifier: Programming Language :: Python :: 3.10
Classifier: Programming Language :: Python :: 3.11
Classifier: Programming Language :: Python :: 3.12
Classifier: Programming Language :: Python :: 3.13
Requires-Dist: bech32 (>=1.2.0,<2.0.0)
Requires-Dist: cffi (>=1.17.1,<2.0.0)
Requires-Dist: ecdsa (>=0.19.0,<0.20.0)
Requires-Dist: eciespy (>=0.4.4,<0.5.0)
Requires-Dist: pycryptodome (>=3.21.0,<4.0.0)
Requires-Dist: pydantic (>=2.8,<3.0)
Requires-Dist: pyjwt (>=2.10.1,<3.0.0)
Requires-Dist: requests (>=2.32.3,<3.0.0)
